analysis/__init__.py
analysis/calcium_analysis.py
analysis/spike_analysis.py
analysis/network_inference/__init__.py
analysis/network_inference/base_inferrer.py
analysis/network_inference/calcium_based_inference.py
analysis/network_inference/spike_based_inference.py
core/__init__.py
core/network_builder.py
core/neuron_models.py
core/spatial.py
core/synapse_models.py
electrophysiology/__init__.py
electrophysiology/brian_monitors.py
electrophysiology/stimulus_generator.py
electrophysiology/data_persistence/__init__.py
electrophysiology/data_persistence/db_schema.py
electrophysiology/data_persistence/sqlite_reader.py
electrophysiology/data_persistence/sqlite_writer.py
mea/__init__.py
mea/mea.py
organoid/__init__.py
organoid/organoid.py
organoid/spatial.py
plasticity/__init__.py
plasticity/base_plasticity_rule.py
plasticity/growth_guidance.py
plasticity/homeostatic.py
plasticity/stdp.py
plasticity/structural_plasticity.py
pybrainorg-1.0.0.dist-info/licenses/LICENSE
simulation/__init__.py
simulation/simulator.py
utils/__init__.py
utils/config_parser.py
visualization/__init__.py
visualization/calcium_plotter.py
visualization/network_plotter.py
visualization/spike_plotter.py
pybrainorg-1.0.0.dist-info/METADATA
pybrainorg-1.0.0.dist-info/WHEEL
pybrainorg-1.0.0.dist-info/top_level.txt
pybrainorg-1.0.0.dist-info/RECORD
