Metadata-Version: 2.4
Name: pybrainorg
Version: 1.0.0
Summary: A Python Brain Organoid Simulator using Brian2.
Home-page: https://github.com/bioquaintum/pybrainorg
Author: Luciano Silva / Bioquaintum Research & Development
Author-email: luciano.silva@bioquaintum.io
Project-URL: Bug Tracker, https://github.com/bioquaintum/pybrainorg/issues
Project-URL: Documentation, https://pybrainorg.readthedocs.io/
Project-URL: Source Code, https://github.com/your_username/pybrainorg
Keywords: brain organoid simulation brian2 neuroscience computational-neuroscience
Classifier: Development Status :: 3 - Alpha
Classifier: Intended Audience :: Science/Research
Classifier: Topic :: Scientific/Engineering :: Bio-Informatics
Classifier: Topic :: Scientific/Engineering :: Medical Science Apps.
Classifier: License :: OSI Approved :: MIT License
Classifier: Operating System :: OS Independent
Classifier: Programming Language :: Python :: 3
Classifier: Programming Language :: Python :: 3.7
Classifier: Programming Language :: Python :: 3.8
Classifier: Programming Language :: Python :: 3.9
Classifier: Programming Language :: Python :: 3.10
Classifier: Programming Language :: Python :: 3.11
Classifier: Natural Language :: English
Requires-Python: >=3.7
License-File: LICENSE
Requires-Dist: brian2>=2.5
Requires-Dist: numpy>=1.20
Requires-Dist: matplotlib>=3.4
Requires-Dist: scipy>=1.7
Requires-Dist: networkx>=2.6
Provides-Extra: dev
Requires-Dist: pytest>=6.0; extra == "dev"
Requires-Dist: flake8>=3.9; extra == "dev"
Requires-Dist: black>=21.0b0; extra == "dev"
Requires-Dist: ipykernel; extra == "dev"
Requires-Dist: jupyterlab; extra == "dev"
Provides-Extra: docs
Requires-Dist: sphinx>=4.0; extra == "docs"
Requires-Dist: sphinx-rtd-theme>=1.0; extra == "docs"
Requires-Dist: nbsphinx>=0.8; extra == "docs"
Requires-Dist: ipykernel; extra == "docs"
Provides-Extra: test
Requires-Dist: pytest>=6.0; extra == "test"
Provides-Extra: all
Requires-Dist: pytest>=6.0; extra == "all"
Requires-Dist: flake8>=3.9; extra == "all"
Requires-Dist: black>=21.0b0; extra == "all"
Requires-Dist: ipykernel; extra == "all"
Requires-Dist: jupyterlab; extra == "all"
Requires-Dist: sphinx>=4.0; extra == "all"
Requires-Dist: sphinx-rtd-theme>=1.0; extra == "all"
Requires-Dist: nbsphinx>=0.8; extra == "all"
Requires-Dist: ipykernel; extra == "all"
Requires-Dist: pytest>=6.0; extra == "all"
Dynamic: author
Dynamic: author-email
Dynamic: classifier
Dynamic: description
Dynamic: description-content-type
Dynamic: home-page
Dynamic: keywords
Dynamic: license-file
Dynamic: project-url
Dynamic: provides-extra
Dynamic: requires-dist
Dynamic: requires-python
Dynamic: summary
